wspd_2/__init__.py
wspd_2/wspd_2.py
WSPD_2-0.1.3.dist-info/LICENSE
WSPD_2-0.1.3.dist-info/METADATA
WSPD_2-0.1.3.dist-info/WHEEL
WSPD_2-0.1.3.dist-info/top_level.txt
WSPD_2-0.1.3.dist-info/RECORD
