Metadata-Version: 2.1
Name: WSPD-2
Version: 0.1.3
Summary: The WSPD_2 Python package
Home-page: https://github.com/dmatijev/wspd_2
Author: Domagoj Matijevic
Author-email: dmatijev@mathos.hr
Classifier: Programming Language :: Python :: 3
Classifier: License :: OSI Approved :: MIT License
Classifier: Operating System :: OS Independent
Requires-Python: >=3.6
License-File: LICENSE
